pym2v/__init__.py
pym2v/api.py
pym2v/constants.py
pym2v/py.typed
pym2v/settings.py
pym2v/types.py
pym2v/utils.py
pym2v-0.1.4.dist-info/licenses/LICENSE
pym2v-0.1.4.dist-info/WHEEL
pym2v-0.1.4.dist-info/METADATA
pym2v-0.1.4.dist-info/RECORD
