Metadata-Version: 2.4
Name: pym2v
Version: 0.1.4
Summary: Python wrapper to interact with the Eurogard m2v IoT platform
Keywords: eurogard,m2v,iot,iiot,api
Author: Stefan Langenbach
Author-email: Stefan Langenbach <stefan.langenbach@bytecare.tech>
License-Expression: AGPL-3.0-only
License-File: LICENSE
Classifier: Development Status :: 4 - Beta
Classifier: Intended Audience :: Developers
Classifier: License :: OSI Approved :: GNU Affero General Public License v3 or later (AGPLv3+)
Classifier: Programming Language :: Python :: 3
Classifier: Topic :: Software Development
Classifier: Typing :: Typed
Requires-Dist: loguru>=0.7.3
Requires-Dist: pandas[excel]>=2.2.3
Requires-Dist: pyarrow>=21.0.0
Requires-Dist: pydantic-settings>=2.6.1
Requires-Dist: requests-oauthlib>=2.0.0
Requires-Dist: tenacity>=9.0.0
Requires-Dist: tqdm>=4.67.1
Maintainer: Stefan Langenbach
Maintainer-email: Stefan Langenbach <stefan.langenbach@bytecare.tech>
Requires-Python: >=3.12
Project-URL: Documentation, https://www.bytecare.tech/pym2v
Project-URL: Homepage, https://www.bytecare.tech
Project-URL: Repository, https://github.com/bytecaretech/pym2v
